asgi_types/__init__.py
asgi_types/py.typed
asgi_types-0.2.0.dist-info/METADATA
asgi_types-0.2.0.dist-info/WHEEL
asgi_types-0.2.0.dist-info/RECORD
